agents/__init__.py
agents/agent_utils.py
agents/alpha_autonomous.py
agents/budget_allocator_autonomous.py
agents/budget_validator_autonomous.py
agents/model_router.py
agents/neuronic_router.py
agents/professor_autonomous.py
agents/rh_ensemble_validator.py
agents/rh_student_profiles.py
agents/session_orchestrator.py
core/__init__.py
core/adaptive_student_scheduler.py
core/agent_creator_manager.py
core/benchmarks.py
core/budget_ledger.py
core/bus_client.py
core/cognitive_affect.py
core/context_pager.py
core/dag_planner.py
core/dense_state_archiver.py
core/dynamic_budget_orchestrator.py
core/error_summary.py
core/executive_loop.py
core/gpia_server.py
core/kb.py
core/meta_cortex.py
core/millennium_goal.py
core/npu_utils.py
core/pass_protocol.py
core/reflex_corrector.py
core/reflex_engine.py
core/response_state_visualizer.py
core/safety_governor.py
core/sandboxed_skill_synthesizer.py
core/settings.py
core/skills_loader.py
core/standard_refinement_engine.py
core/stubs.py
core/system_test.py
core/temporal_pulse.py
core/worker.py
core/agents/__init__.py
core/agents/base.py
core/dense_logic/__init__.py
core/dense_logic/decoder.py
core/kernel/__init__.py
core/kernel/budget_service.py
core/kernel/preflight.py
core/kernel/services.py
core/kernel/switchboard.py
core/mcp_skill/__init__.py
core/mcp_skill/interfaces.py
core/mcp_skill/mcp_skill.py
core/mcp_skill/orchestrator.py
core/mcp_skill/state_machine.py
core/modes/__init__.py
core/modes/base.py
core/modes/forensic_debug.py
core/modes/manifest.py
core/modes/sovereign.py
core/modes/sovereign_loop.py
core/modes/teaching.py
core/resonant_kernel/__init__.py
core/resonant_kernel/interface.py
core/sovereignty_v2/__init__.py
core/sovereignty_v2/heuristics_registry.py
core/sovereignty_v2/identity_checker.py
core/sovereignty_v2/rollback_gate.py
core/sovereignty_v2/sovereignty_wrapper.py
core/sovereignty_v2/telemetry_observer.py
governor/__init__.py
governor/policy_engine_v1/__init__.py
governor/policy_engine_v1/meta_critic.py
gpia_agi_server-0.1.0.dist-info/licenses/LICENSE
gpia_agi_server-0.1.0.dist-info/licenses/NOTICE
gpia_agi_server-0.1.0.dist-info/METADATA
gpia_agi_server-0.1.0.dist-info/WHEEL
gpia_agi_server-0.1.0.dist-info/entry_points.txt
gpia_agi_server-0.1.0.dist-info/top_level.txt
gpia_agi_server-0.1.0.dist-info/RECORD
