Metadata-Version: 2.4
Name: gpia-agi-server
Version: 0.1.0
Summary: A self-evolving cognitive AGI server with active immunity and Dense-State memory.
Author-email: Cloudhabil Contributors <obe@cloudhabil.com>
License: Apache-2.0
Project-URL: Homepage, https://github.com/Cloudhabil/AGI-Server
Project-URL: Bug Tracker, https://github.com/Cloudhabil/AGI-Server/issues
Project-URL: Documentation, https://github.com/Cloudhabil/AGI-Server/tree/main/docs
Keywords: agi,cognitive-computing,autonomous-agents,self-evolving,ai-safety
Classifier: Development Status :: 4 - Beta
Classifier: Intended Audience :: Science/Research
Classifier: Topic :: Scientific/Engineering :: Artificial Intelligence
Classifier: License :: OSI Approved :: Apache Software License
Classifier: Programming Language :: Python :: 3.11
Classifier: Operating System :: OS Independent
Classifier: Environment :: Console
Requires-Python: >=3.11
License-File: LICENSE
License-File: NOTICE
Requires-Dist: python-dotenv==1.0.1
Requires-Dist: requests==2.32.3
Requires-Dist: jinja2==3.1.4
Requires-Dist: rapidfuzz==3.10.0
Requires-Dist: typer==0.12.3
Requires-Dist: rich==13.7.1
Requires-Dist: fastapi==0.112.2
Requires-Dist: uvicorn==0.30.6
Requires-Dist: pydantic==2.8.2
Requires-Dist: pyyaml==6.0.2
Requires-Dist: anyio==4.4.0
Requires-Dist: python-multipart==0.0.20
Requires-Dist: numpy==1.26.4
Requires-Dist: redis>=5.0
Requires-Dist: async-timeout==4.0.3
Requires-Dist: asyncpg>=0.29
Requires-Dist: google-api-python-client==2.147.0
Requires-Dist: google-auth==2.33.0
Requires-Dist: google-auth-oauthlib==1.2.1
Requires-Dist: google-auth-httplib2==0.2.0
Requires-Dist: stripe==9.8.0
Requires-Dist: email-validator==2.2.0
Requires-Dist: pydantic-settings>=2.4
Requires-Dist: apscheduler
Requires-Dist: sympy>=1.12
Requires-Dist: mpmath>=1.3.0
Requires-Dist: scipy>=1.11.0
Requires-Dist: arxiv>=2.0.0
Provides-Extra: dev
Requires-Dist: pytest>=8.3.2; extra == "dev"
Requires-Dist: pytest-asyncio>=0.23; extra == "dev"
Requires-Dist: mypy>=1.10; extra == "dev"
Requires-Dist: ruff>=0.5; extra == "dev"
Requires-Dist: flake8==7.1.1; extra == "dev"
Requires-Dist: httpx>=0.27; extra == "dev"
Provides-Extra: token
Requires-Dist: tiktoken>=0.7; extra == "token"
Provides-Extra: observability
Requires-Dist: prometheus-fastapi-instrumentator>=5.9.0; extra == "observability"
Requires-Dist: opentelemetry-api==1.25.0; extra == "observability"
Requires-Dist: opentelemetry-sdk==1.25.0; extra == "observability"
Requires-Dist: opentelemetry-exporter-otlp==1.25.0; extra == "observability"
Requires-Dist: opentelemetry-instrumentation-fastapi==0.46b0; extra == "observability"
Requires-Dist: opentelemetry-instrumentation-logging==0.46b0; extra == "observability"
Provides-Extra: faiss
Requires-Dist: faiss-cpu>=1.8.0; extra == "faiss"
Dynamic: license-file
